mqttservice/__init__.py
mqttservice/mqttbaseservice.py
mqttservice/mqttpatternmatcher.py
pymqttmicroservicebase_tspspi-0.0.1a0.dist-info/LICENSE.md
pymqttmicroservicebase_tspspi-0.0.1a0.dist-info/METADATA
pymqttmicroservicebase_tspspi-0.0.1a0.dist-info/WHEEL
pymqttmicroservicebase_tspspi-0.0.1a0.dist-info/top_level.txt
pymqttmicroservicebase_tspspi-0.0.1a0.dist-info/RECORD
