Metadata-Version: 2.1
Name: pymqttmicroservicebase-tspspi
Version: 0.0.1a0
Summary: A basis library for MQTT based microservices in Python
Home-page: https://github.com/tspspi/pymqttmicroservicebase
Author: Thomas Spielauer
Author-email: pypipackages01@tspi.at
Classifier: Programming Language :: Python :: 3
Classifier: License :: OSI Approved :: BSD License
Classifier: Operating System :: OS Independent
Requires-Python: >=3.6
License-File: LICENSE.md
Requires-Dist: paho-mqtt (>=1.6.1)
Requires-Dist: daemonize (>=2.5.0)
Requires-Dist: lockfile (>=0.12.2)
